easyvalid_data_validator/__init__.py
easyvalid_data_validator/common.py
easyvalid_data_validator/constraints.py
easyvalid_data_validator/customexceptions/__init__.py
easyvalid_data_validator/customexceptions/array.py
easyvalid_data_validator/customexceptions/common.py
easyvalid_data_validator/customexceptions/integer.py
easyvalid_data_validator/customexceptions/string.py
easyvalid_data_validator/datacheckers/__init__.py
easyvalid_data_validator/datacheckers/array_checker.py
easyvalid_data_validator/datacheckers/boolean_checker.py
easyvalid_data_validator/datacheckers/dictionary_checker.py
easyvalid_data_validator/datacheckers/float_checker.py
easyvalid_data_validator/datacheckers/integer_checker.py
easyvalid_data_validator/datacheckers/string_checker.py
easyvalid_data_validator/validator.py
easyvalid_data_validator-2.0.1.dist-info/METADATA
easyvalid_data_validator-2.0.1.dist-info/WHEEL
easyvalid_data_validator-2.0.1.dist-info/RECORD
